.gitignore
MANIFEST.in
README.txt
bootstrap.py
buildout.cfg
setup.cfg
setup.py
bise/__init__.py
bise.biodiversityfactsheet.egg-info/PKG-INFO
bise.biodiversityfactsheet.egg-info/SOURCES.txt
bise.biodiversityfactsheet.egg-info/dependency_links.txt
bise.biodiversityfactsheet.egg-info/entry_points.txt
bise.biodiversityfactsheet.egg-info/namespace_packages.txt
bise.biodiversityfactsheet.egg-info/not-zip-safe
bise.biodiversityfactsheet.egg-info/paster_plugins.txt
bise.biodiversityfactsheet.egg-info/requires.txt
bise.biodiversityfactsheet.egg-info/top_level.txt
bise/biodiversityfactsheet/INTEGRATION.txt
bise/biodiversityfactsheet/__init__.py
bise/biodiversityfactsheet/biodiversityfactsheet.py
bise/biodiversityfactsheet/cataloguer.py
bise/biodiversityfactsheet/configure.zcml
bise/biodiversityfactsheet/fact.py
bise/biodiversityfactsheet/permissions.zcml
bise/biodiversityfactsheet/section.py
bise/biodiversityfactsheet/tests.py
bise/biodiversityfactsheet/browser/__init__.py
bise/biodiversityfactsheet/browser/cataloguer.py
bise/biodiversityfactsheet/browser/configure.zcml
bise/biodiversityfactsheet/locales/README.txt
bise/biodiversityfactsheet/profiles/default/cssregistry.xml
bise/biodiversityfactsheet/profiles/default/diff_tool.xml
bise/biodiversityfactsheet/profiles/default/jsregistry.xml
bise/biodiversityfactsheet/profiles/default/metadata.xml
bise/biodiversityfactsheet/profiles/default/rolemap.xml
bise/biodiversityfactsheet/profiles/default/tinymce.xml
bise/biodiversityfactsheet/profiles/default/types.xml
bise/biodiversityfactsheet/profiles/default/types/BiodiversityFactsheet.xml
bise/biodiversityfactsheet/profiles/default/types/Fact.xml
bise/biodiversityfactsheet/profiles/default/types/Section.xml
bise/biodiversityfactsheet/static/EEACreateContent.js
bise/biodiversityfactsheet/static/app.js
bise/biodiversityfactsheet/static/commonConfig.js
bise/biodiversityfactsheet/static/custommenu.js
bise/biodiversityfactsheet/static/jquery.collapsible.min.js
bise/biodiversityfactsheet/static/layout.js
bise/biodiversityfactsheet/static/maps.js
bise/biodiversityfactsheet/static/mapsConfig.js
bise/biodiversityfactsheet/static/nls/template.js
bise/biodiversityfactsheet/templates/biodiversityfactsheetview.pt
bise/biodiversityfactsheet/templates/factrenderview.pt
bise/biodiversityfactsheet/templates/factview.pt
bise/biodiversityfactsheet/upgrades/1_2.py
bise/biodiversityfactsheet/upgrades/2_3.py
bise/biodiversityfactsheet/upgrades/__init__.py
