Metadata-Version: 1.1
Name: bise.biodiversityfactsheet
Version: 1.3
Summary: Content-types to manage Biodiversity factsheets
Home-page: https://github.com/eea/bise.biodiversityfactsheet
Author: Mikel Larreategi
Author-email: mlarreategi@codesyntax.com
License: GPL
Platform: UNKNOWN
Classifier: Framework :: Plone
Classifier: Programming Language :: Python
Classifier: Topic :: Software Development :: Libraries :: Python Modules
